{
  "global": {
    "core": {
      "corecolorprimary": {
        "$value": "{SportBILD.blue.spobiBlue016}",
        "$type": "color",
        "$description": "Bild: 046; SpoBi: 016 current css calls this variable main tenant color",
        "$extensions": {
          "com.figma": {
            "id": "VariableID:18212:14496",
            "variableCollectionId": "VariableCollectionId:18212:14495",
            "scopes": [],
            "hiddenFromPublishing": true,
            "resolvedType": "COLOR"
          }
        }
      },
      "corecolorsecondary": {
        "$value": "{BILD.neutral.BILD100}",
        "$type": "color",
        "$description": "Bild&SpoBi Tone 100",
        "$extensions": {
          "com.figma": {
            "id": "VariableID:18213:564",
            "variableCollectionId": "VariableCollectionId:18212:14495",
            "scopes": [],
            "hiddenFromPublishing": true,
            "resolvedType": "COLOR"
          }
        }
      },
      "corecolorsecondarydark": {
        "$value": "{SportBILD.blue.spobiBlue010}",
        "$type": "color",
        "$description": "Bild: 015 ; SpoBi: 010",
        "$extensions": {
          "com.figma": {
            "id": "VariableID:18213:565",
            "variableCollectionId": "VariableCollectionId:18212:14495",
            "scopes": [],
            "hiddenFromPublishing": true,
            "resolvedType": "COLOR"
          }
        }
      },
      "corecolortertiary": {
        "$value": "{SportBILD.blue.spobiBlue010}",
        "$type": "color",
        "$description": "Bild: 015 ; SpoBi: 010",
        "$extensions": {
          "com.figma": {
            "id": "VariableID:18213:566",
            "variableCollectionId": "VariableCollectionId:18212:14495",
            "scopes": [],
            "hiddenFromPublishing": true,
            "resolvedType": "COLOR"
          }
        }
      },
      "corecolortertiarydark": {
        "$value": "{BILD.neutral.BILD100}",
        "$type": "color",
        "$description": "Bild&SpoBi: 100",
        "$extensions": {
          "com.figma": {
            "id": "VariableID:18213:567",
            "variableCollectionId": "VariableCollectionId:18212:14495",
            "scopes": [],
            "hiddenFromPublishing": true,
            "resolvedType": "COLOR"
          }
        }
      }
    },
    "attention": {
      "accentcolorprimary": {
        "$value": "{SportBILD.blue.spobiBlue029}",
        "$type": "color",
        "$description": "Bild: Tone 046 ; SpoBi: 016 This variable is used on small UI elements such as the background color for kickers.",
        "$extensions": {
          "com.figma": {
            "id": "VariableID:18213:568",
            "variableCollectionId": "VariableCollectionId:18212:14495",
            "scopes": [],
            "hiddenFromPublishing": true,
            "resolvedType": "COLOR"
          }
        }
      },
      "accentcolorprimarydark": {
        "$value": "{SportBILD.blue.spobiBlue098}",
        "$type": "color",
        "$description": "Bild: 100 ; SpoBi: 098",
        "$extensions": {
          "com.figma": {
            "id": "VariableID:18213:569",
            "variableCollectionId": "VariableCollectionId:18212:14495",
            "scopes": [],
            "hiddenFromPublishing": true,
            "resolvedType": "COLOR"
          }
        }
      }
    },
    "surface": {
      "surfacecolorprimary": {
        "$value": "{BILD.neutral.BILD100}",
        "$type": "color",
        "$description": "Bild: 100 ; SpoBi: 100",
        "$extensions": {
          "com.figma": {
            "id": "VariableID:18213:570",
            "variableCollectionId": "VariableCollectionId:18212:14495",
            "scopes": [],
            "hiddenFromPublishing": true,
            "resolvedType": "COLOR"
          }
        }
      },
      "surfacecolorprimarydark": {
        "$value": "{SportBILD.blue.spobiBlue010}",
        "$type": "color",
        "$description": "Bild: 015 ; SpoBi: 010",
        "$extensions": {
          "com.figma": {
            "id": "VariableID:18213:571",
            "variableCollectionId": "VariableCollectionId:18212:14495",
            "scopes": [],
            "hiddenFromPublishing": true,
            "resolvedType": "COLOR"
          }
        }
      },
      "surfacecolorsecondary": {
        "$value": "{SportBILD.blue.spobiBlue098}",
        "$type": "color",
        "$description": "Bild: 096 ; SpoBi: 098",
        "$extensions": {
          "com.figma": {
            "id": "VariableID:18215:572",
            "variableCollectionId": "VariableCollectionId:18212:14495",
            "scopes": [],
            "hiddenFromPublishing": true,
            "resolvedType": "COLOR"
          }
        }
      },
      "surfacecolorsecondarydark": {
        "$value": "{SportBILD.blue.spobiBlue016}",
        "$type": "color",
        "$description": "Bild: 020 ; SpoBi: 016",
        "$extensions": {
          "com.figma": {
            "id": "VariableID:18215:573",
            "variableCollectionId": "VariableCollectionId:18212:14495",
            "scopes": [],
            "hiddenFromPublishing": true,
            "resolvedType": "COLOR"
          }
        }
      },
      "surfacecolortertiary": {
        "$value": "{SportBILD.blue.spobiBlue081}",
        "$type": "color",
        "$description": "Bild: 093 ; SpoBi: 081",
        "$extensions": {
          "com.figma": {
            "id": "VariableID:18215:576",
            "variableCollectionId": "VariableCollectionId:18212:14495",
            "scopes": [],
            "hiddenFromPublishing": true,
            "resolvedType": "COLOR"
          }
        }
      },
      "surfacecolortertiarydark": {
        "$value": "{SportBILD.blue.spobiBlue029}",
        "$type": "color",
        "$description": "Bild: 025 ; SpoBi: 029",
        "$extensions": {
          "com.figma": {
            "id": "VariableID:18215:577",
            "variableCollectionId": "VariableCollectionId:18212:14495",
            "scopes": [],
            "hiddenFromPublishing": true,
            "resolvedType": "COLOR"
          }
        }
      },
      "surfacecolorquartenary": {
        "$value": "{BILD.gray.BILD085}",
        "$type": "color",
        "$description": "Bild: 085 ; SpoBi: 085",
        "$extensions": {
          "com.figma": {
            "id": "VariableID:18215:578",
            "variableCollectionId": "VariableCollectionId:18212:14495",
            "scopes": [],
            "hiddenFromPublishing": true,
            "resolvedType": "COLOR"
          }
        }
      },
      "surfacecolorquartenarydark": {
        "$value": "{BILD.gray.BILD035}",
        "$type": "color",
        "$description": "Bild: 035 ; SpoBi: 035",
        "$extensions": {
          "com.figma": {
            "id": "VariableID:18215:579",
            "variableCollectionId": "VariableCollectionId:18212:14495",
            "scopes": [],
            "hiddenFromPublishing": true,
            "resolvedType": "COLOR"
          }
        }
      }
    },
    "state": {
      "colorprimaryactive": {
        "$value": "{SportBILD.blue.spobiBlue029}",
        "$type": "color",
        "$description": "Bild: 046 ; SpoBi: 029",
        "$extensions": {
          "com.figma": {
            "id": "VariableID:18215:583",
            "variableCollectionId": "VariableCollectionId:18212:14495",
            "scopes": [],
            "hiddenFromPublishing": true,
            "resolvedType": "COLOR"
          }
        }
      },
      "colorprimaryactivedark": {
        "$value": "{SportBILD.blue.spobiBlue098}",
        "$type": "color",
        "$description": "Bild: 046 ; SpoBi: 098",
        "$extensions": {
          "com.figma": {
            "id": "VariableID:18215:584",
            "variableCollectionId": "VariableCollectionId:18212:14495",
            "scopes": [],
            "hiddenFromPublishing": true,
            "resolvedType": "COLOR"
          }
        }
      }
    },
    "text": {
      "textcolorprimary": {
        "$value": "{BILD.gray.BILD015}",
        "$type": "color",
        "$description": "Bild & SpoBi: Tone 015",
        "$extensions": {
          "com.figma": {
            "id": "VariableID:18215:585",
            "variableCollectionId": "VariableCollectionId:18212:14495",
            "scopes": [],
            "hiddenFromPublishing": true,
            "resolvedType": "COLOR"
          }
        }
      },
      "textcolorprimarydark": {
        "$value": "{BILD.gray.BILD093}",
        "$type": "color",
        "$description": "Bild & SpoBi: Tone 093",
        "$extensions": {
          "com.figma": {
            "id": "VariableID:18215:586",
            "variableCollectionId": "VariableCollectionId:18212:14495",
            "scopes": [],
            "hiddenFromPublishing": true,
            "resolvedType": "COLOR"
          }
        }
      },
      "headlinecolorprimary": {
        "$value": "{SportBILD.blue.spobiBlue016}",
        "$type": "color",
        "$description": "Bild: 015 ; SpoBi: 016",
        "$extensions": {
          "com.figma": {
            "id": "VariableID:18215:587",
            "variableCollectionId": "VariableCollectionId:18212:14495",
            "scopes": [],
            "hiddenFromPublishing": true,
            "resolvedType": "COLOR"
          }
        }
      },
      "headlinecolorprimarydark": {
        "$value": "{BILD.neutral.BILD100}",
        "$type": "color",
        "$description": "Bild&SpoBi: Tone 100",
        "$extensions": {
          "com.figma": {
            "id": "VariableID:18215:588",
            "variableCollectionId": "VariableCollectionId:18212:14495",
            "scopes": [],
            "hiddenFromPublishing": true,
            "resolvedType": "COLOR"
          }
        }
      },
      "kickertextcoloronbg": {
        "$value": "{BILD.neutral.BILD100}",
        "$type": "color",
        "$description": "This variable is used on kicker texts that are on top of a color that is different from the outer color of the overall user interface. Bild & SpoBi: Tone 100",
        "$extensions": {
          "com.figma": {
            "id": "VariableID:18215:589",
            "variableCollectionId": "VariableCollectionId:18212:14495",
            "scopes": [],
            "hiddenFromPublishing": true,
            "resolvedType": "COLOR"
          }
        }
      },
      "kickertextcoloronsurface": {
        "$value": "{BILD.gray.BILD060}",
        "$type": "color",
        "$description": "This variable is used for the color of kicker texts that are not no top of a different color of the overall user interface. Bild: 046 ; SpoBi: 060",
        "$extensions": {
          "com.figma": {
            "id": "VariableID:18215:590",
            "variableCollectionId": "VariableCollectionId:18212:14495",
            "scopes": [],
            "hiddenFromPublishing": true,
            "resolvedType": "COLOR"
          }
        }
      },
      "kickertextcoloronsurfacedark": {
        "$value": "{BILD.gray.BILD060}",
        "$type": "color",
        "$description": "Use this variable for kicker texts that are directly on top of the color of the overall user interface. Bild & SpoBi tone 060.",
        "$extensions": {
          "com.figma": {
            "id": "VariableID:18215:593",
            "variableCollectionId": "VariableCollectionId:18212:14495",
            "scopes": [],
            "hiddenFromPublishing": true,
            "resolvedType": "COLOR"
          }
        }
      },
      "textcolorsecondary": {
        "$value": "{BILD.gray.BILD060}",
        "$type": "color",
        "$description": "Bild & SpoBi: Tone 060",
        "$extensions": {
          "com.figma": {
            "id": "VariableID:18218:9878",
            "variableCollectionId": "VariableCollectionId:18212:14495",
            "scopes": [],
            "hiddenFromPublishing": true,
            "resolvedType": "COLOR"
          }
        }
      },
      "textcolorsecondarydark": {
        "$value": "{BILD.gray.BILD060}",
        "$type": "color",
        "$description": "Bild & SpoBi: Tone 060",
        "$extensions": {
          "com.figma": {
            "id": "VariableID:18218:9879",
            "variableCollectionId": "VariableCollectionId:18212:14495",
            "scopes": [],
            "hiddenFromPublishing": true,
            "resolvedType": "COLOR"
          }
        }
      },
      "kickerbgcoloronsurface": {
        "$value": "{SportBILD.blue.spobiBlue029}",
        "$type": "color",
        "$description": "Use this variable for the color immediately behind the bounding box of the kicker text element. Bild: 046 ; SpoBi: 029",
        "$extensions": {
          "com.figma": {
            "id": "VariableID:18342:23968",
            "variableCollectionId": "VariableCollectionId:18212:14495",
            "scopes": [],
            "hiddenFromPublishing": true,
            "resolvedType": "COLOR"
          }
        }
      },
      "kickerbgcoloronsurfacedark": {
        "$value": "{BILD.gray.BILD060}",
        "$type": "color",
        "$description": "Use this variable for the dark mode color of the background immediately around the kicker text element. Bild: 060 ; SpoBi: 060",
        "$extensions": {
          "com.figma": {
            "id": "VariableID:18342:23969",
            "variableCollectionId": "VariableCollectionId:18212:14495",
            "scopes": [],
            "hiddenFromPublishing": true,
            "resolvedType": "COLOR"
          }
        }
      }
    }
  },
  "component": {
    "button": {
      "primaryneutral": {
        "buttonprimarybgcoloridle": {
          "$value": "{BILD.gray.BILD015}",
          "$type": "color",
          "$description": "Bild & SpoBi: Tone 015",
          "$extensions": {
            "com.figma": {
              "id": "VariableID:18343:22649",
              "variableCollectionId": "VariableCollectionId:18212:14495",
              "scopes": [],
              "hiddenFromPublishing": true,
              "resolvedType": "COLOR"
            }
          }
        },
        "buttonprimarybgcolorhover": {
          "$value": "{BILD.gray.BILD035}",
          "$type": "color",
          "$description": "Bild & SpoBi: Tone 035",
          "$extensions": {
            "com.figma": {
              "id": "VariableID:18343:26495",
              "variableCollectionId": "VariableCollectionId:18212:14495",
              "scopes": [],
              "hiddenFromPublishing": true,
              "resolvedType": "COLOR"
            }
          }
        },
        "buttonprimarybgcoloridledark": {
          "$value": "{BILD.neutral.BILD100}",
          "$type": "color",
          "$description": "Bild & SpoBi: Tone 100",
          "$extensions": {
            "com.figma": {
              "id": "VariableID:18356:65364",
              "variableCollectionId": "VariableCollectionId:18212:14495",
              "scopes": [],
              "hiddenFromPublishing": true,
              "resolvedType": "COLOR"
            }
          }
        },
        "buttonprimarybgcolorhoverdark": {
          "$value": "{SportBILD.blue.spobiBlue081}",
          "$type": "color",
          "$description": "Bild: 093 ; SpoBi: 081",
          "$extensions": {
            "com.figma": {
              "id": "VariableID:18356:65365",
              "variableCollectionId": "VariableCollectionId:18212:14495",
              "scopes": [],
              "hiddenFromPublishing": true,
              "resolvedType": "COLOR"
            }
          }
        }
      },
      "primarybrand": {
        "buttonprimarybgcoloridle": {
          "$value": "{SportBILD.blue.spobiBlue029}",
          "$type": "color",
          "$description": "Bild: 046 ; SpoBi: 029",
          "$extensions": {
            "com.figma": {
              "id": "VariableID:18454:32957",
              "variableCollectionId": "VariableCollectionId:18212:14495",
              "scopes": [],
              "hiddenFromPublishing": true,
              "resolvedType": "COLOR"
            }
          }
        },
        "buttonprimarybgcoloridledark": {
          "$value": "{SportBILD.blue.spobiBlue038}",
          "$type": "color",
          "$description": "This variable controls the primary button idle color for two brands in dark mode. Bild: 046 ; SpoBi: 038",
          "$extensions": {
            "com.figma": {
              "id": "VariableID:18454:32958",
              "variableCollectionId": "VariableCollectionId:18212:14495",
              "scopes": [],
              "hiddenFromPublishing": true,
              "resolvedType": "COLOR"
            }
          }
        },
        "buttonprimarybgcolorhover": {
          "$value": "{SportBILD.blue.spobiBlue016}",
          "$type": "color",
          "$description": "Bild: 035 ; SpoBi: 016",
          "$extensions": {
            "com.figma": {
              "id": "VariableID:18454:32959",
              "variableCollectionId": "VariableCollectionId:18212:14495",
              "scopes": [],
              "hiddenFromPublishing": true,
              "resolvedType": "COLOR"
            }
          }
        },
        "buttonprimarybgcolorhoverdark": {
          "$value": "{SportBILD.blue.spobiBlue029}",
          "$type": "color",
          "$description": "This variable stores colors for the hover state of primary buttons for two brands in dark mode. Bild: 035 ; SpoBi: 029",
          "$extensions": {
            "com.figma": {
              "id": "VariableID:18454:32960",
              "variableCollectionId": "VariableCollectionId:18212:14495",
              "scopes": [],
              "hiddenFromPublishing": true,
              "resolvedType": "COLOR"
            }
          }
        }
      }
    },
    "breakingnews": {
      "breakingnewstextcontentcolor": {
        "$value": "{BILD.gray.BILD015}",
        "$type": "color",
        "$description": "This variable is used on the text for headlines in the horizontally animated breaking news strip. Bild: 100 ; SpoBi: 015",
        "$extensions": {
          "com.figma": {
            "id": "VariableID:18345:42065",
            "variableCollectionId": "VariableCollectionId:18212:14495",
            "scopes": [],
            "hiddenFromPublishing": true,
            "resolvedType": "COLOR"
          }
        }
      },
      "breakingnewssurfacecolor": {
        "$value": "{BILD.yellow.BILDYellow}",
        "$type": "color",
        "$description": "This variable is used on the breaking news strip that has horizontally animated headlines. Bild: 015 ; SpoBi: 081",
        "$extensions": {
          "com.figma": {
            "id": "VariableID:18345:42066",
            "variableCollectionId": "VariableCollectionId:18212:14495",
            "scopes": [],
            "hiddenFromPublishing": true,
            "resolvedType": "COLOR"
          }
        }
      },
      "breakingnewstitlesurfacecolor": {
        "$value": "{SportBILD.blue.spobiBlue016}",
        "$type": "color",
        "$description": "This variable is used for the background color of the \"Breaking News\" title. Bild: 067 ; SpoBi: 016",
        "$extensions": {
          "com.figma": {
            "id": "VariableID:18345:42067",
            "variableCollectionId": "VariableCollectionId:18212:14495",
            "scopes": [],
            "hiddenFromPublishing": true,
            "resolvedType": "COLOR"
          }
        }
      },
      "breakingnewstoptitletextcolor": {
        "$value": "{BILD.yellow.BILDYellow}",
        "$type": "color",
        "$description": "This variable is used for the color of the \"breaking\" word in the \"breaking news\" horizontally animated headlines strip. Bild: 010 ; SpoBi: 081",
        "$extensions": {
          "com.figma": {
            "id": "VariableID:18345:42068",
            "variableCollectionId": "VariableCollectionId:18212:14495",
            "scopes": [],
            "hiddenFromPublishing": true,
            "resolvedType": "COLOR"
          }
        }
      },
      "breakingnewssurfacecolordark": {
        "$value": "{BILD.yellow.BILDYellow}",
        "$type": "color",
        "$description": "This variable is for the background color of the horizontally animated strip with headlines for breaking news on dark mode.  Bild: 093 ; SpoBi: 081",
        "$extensions": {
          "com.figma": {
            "id": "VariableID:18345:42069",
            "variableCollectionId": "VariableCollectionId:18212:14495",
            "scopes": [],
            "hiddenFromPublishing": true,
            "resolvedType": "COLOR"
          }
        }
      },
      "breakingnewstextcontentcolordark": {
        "$value": "{BILD.gray.BILD015}",
        "$type": "color",
        "$description": "This variable is used on the text for headlines in the horizontally animated breaking news strip on dark mode. Bild&SpoBi: 015",
        "$extensions": {
          "com.figma": {
            "id": "VariableID:18345:42070",
            "variableCollectionId": "VariableCollectionId:18212:14495",
            "scopes": [],
            "hiddenFromPublishing": true,
            "resolvedType": "COLOR"
          }
        }
      },
      "breakingnewsbottomtitletextcolor": {
        "$value": "{BILD.neutral.BILD100}",
        "$type": "color",
        "$description": "This variable is used for the color of the \"News\" word in the breaking news horizontal animated headlines strip. Bild: 010 ; SpoBi: 100",
        "$extensions": {
          "com.figma": {
            "id": "VariableID:18345:42309",
            "variableCollectionId": "VariableCollectionId:18212:14495",
            "scopes": [],
            "hiddenFromPublishing": true,
            "resolvedType": "COLOR"
          }
        }
      }
    },
    "teaser": {
      "teasertitlebackgroundgradientstart": {
        "$value": "{SportBILD.alpha.spobiBlue016-alpha70}",
        "$type": "color",
        "$extensions": {
          "com.figma": {
            "id": "VariableID:18355:65198",
            "variableCollectionId": "VariableCollectionId:18212:14495",
            "scopes": [],
            "hiddenFromPublishing": true,
            "resolvedType": "COLOR"
          }
        }
      },
      "teasertitlebackgroundgradientstop": {
        "$value": "{SportBILD.alpha.spobiBlue016-alpha0}",
        "$type": "color",
        "$extensions": {
          "com.figma": {
            "id": "VariableID:18355:65199",
            "variableCollectionId": "VariableCollectionId:18212:14495",
            "scopes": [],
            "hiddenFromPublishing": true,
            "resolvedType": "COLOR"
          }
        }
      }
    },
    "menu": {
      "menulinklanesurfacecolor": {
        "$value": "{SportBILD.blue.spobiBlue016}",
        "$type": "color",
        "$description": "This variable is used for making possible the default color difference between the Bild and SportBild link lanes inside the menu component.",
        "$extensions": {
          "com.figma": {
            "id": "VariableID:18631:74156",
            "variableCollectionId": "VariableCollectionId:18212:14495",
            "scopes": [],
            "hiddenFromPublishing": true,
            "resolvedType": "COLOR"
          }
        }
      },
      "menulinklanelabelcolor": {
        "$value": "{BILD.gray.BILD085}",
        "$type": "color",
        "$description": "This variable is used for making possible the default color difference between the Bild and SportBild link lane labels inside the menu component.",
        "$extensions": {
          "com.figma": {
            "id": "VariableID:18631:74157",
            "variableCollectionId": "VariableCollectionId:18212:14495",
            "scopes": [],
            "hiddenFromPublishing": true,
            "resolvedType": "COLOR"
          }
        }
      },
      "menulinklanelabelcolordark": {
        "$value": "{BILD.gray.BILD073}",
        "$type": "color",
        "$extensions": {
          "com.figma": {
            "id": "VariableID:18631:80971",
            "variableCollectionId": "VariableCollectionId:18212:14495",
            "scopes": [],
            "hiddenFromPublishing": true,
            "resolvedType": "COLOR"
          }
        }
      },
      "menulinklanesurfacecolordark": {
        "$value": "{SportBILD.blue.spobiBlue016}",
        "$type": "color",
        "$description": "This variable is used for making possible the default color difference between the Bild and SportBild link lanes inside the menu component on Dark mode.",
        "$extensions": {
          "com.figma": {
            "id": "VariableID:18631:80972",
            "variableCollectionId": "VariableCollectionId:18212:14495",
            "scopes": [],
            "hiddenFromPublishing": true,
            "resolvedType": "COLOR"
          }
        }
      },
      "menulinkcolorborderactive": {
        "$value": "{SportBILD.blue.spobiBlue016}",
        "$type": "color",
        "$extensions": {
          "com.figma": {
            "id": "VariableID:18644:81007",
            "variableCollectionId": "VariableCollectionId:18212:14495",
            "scopes": [],
            "hiddenFromPublishing": true,
            "resolvedType": "COLOR"
          }
        }
      },
      "menulinkcolorborderactivedark": {
        "$value": "{SportBILD.blue.spobiBlue098}",
        "$type": "color",
        "$extensions": {
          "com.figma": {
            "id": "VariableID:18644:81008",
            "variableCollectionId": "VariableCollectionId:18212:14495",
            "scopes": [],
            "hiddenFromPublishing": true,
            "resolvedType": "COLOR"
          }
        }
      },
      "menulinklanelabelcoloractive": {
        "$value": "{BILD.neutral.BILD100}",
        "$type": "color",
        "$description": "This variable is used for making possible the active color difference between the Bild and SportBild link lane labels inside the menu component.",
        "$extensions": {
          "com.figma": {
            "id": "VariableID:18644:81009",
            "variableCollectionId": "VariableCollectionId:18212:14495",
            "scopes": [],
            "hiddenFromPublishing": true,
            "resolvedType": "COLOR"
          }
        }
      },
      "apptopbarsurfacecolor": {
        "$value": "{Global.Surface.surfaceColorSecondaryDark}",
        "$type": "color",
        "$extensions": {
          "com.figma": {
            "id": "VariableID:18710:4112",
            "variableCollectionId": "VariableCollectionId:18212:14495",
            "scopes": [],
            "hiddenFromPublishing": true,
            "resolvedType": "COLOR"
          }
        }
      },
      "apptopbarbgcolordark": {
        "$value": "{Global.Surface.surfaceColorSecondaryDark}",
        "$type": "color",
        "$extensions": {
          "com.figma": {
            "id": "VariableID:18710:4113",
            "variableCollectionId": "VariableCollectionId:18212:14495",
            "scopes": [],
            "hiddenFromPublishing": true,
            "resolvedType": "COLOR"
          }
        }
      },
      "appbottomtabbarbgcolor": {
        "$value": "{Global.Surface.surfaceColorPrimary}",
        "$type": "color",
        "$extensions": {
          "com.figma": {
            "id": "VariableID:18961:4492",
            "variableCollectionId": "VariableCollectionId:18212:14495",
            "scopes": [],
            "hiddenFromPublishing": true,
            "resolvedType": "COLOR"
          }
        }
      },
      "appbottomtabbarbgdark": {
        "$value": "{Global.Surface.surfaceColorSecondaryDark}",
        "$type": "color",
        "$extensions": {
          "com.figma": {
            "id": "VariableID:18961:4493",
            "variableCollectionId": "VariableCollectionId:18212:14495",
            "scopes": [],
            "hiddenFromPublishing": true,
            "resolvedType": "COLOR"
          }
        }
      },
      "apptopbariconcolor": {
        "$value": "{BILD.gray.BILD060}",
        "$type": "color",
        "$extensions": {
          "com.figma": {
            "id": "VariableID:18961:17140",
            "variableCollectionId": "VariableCollectionId:18212:14495",
            "scopes": [],
            "hiddenFromPublishing": true,
            "resolvedType": "COLOR"
          }
        }
      },
      "apptopbariconcolordark": {
        "$value": "{BILD.gray.BILD060}",
        "$type": "color",
        "$extensions": {
          "com.figma": {
            "id": "VariableID:18961:17141",
            "variableCollectionId": "VariableCollectionId:18212:14495",
            "scopes": [],
            "hiddenFromPublishing": true,
            "resolvedType": "COLOR"
          }
        }
      },
      "apptopbartextcolor": {
        "$value": "{Global.Text.textColorPrimaryDark}",
        "$type": "color",
        "$extensions": {
          "com.figma": {
            "id": "VariableID:18961:17143",
            "variableCollectionId": "VariableCollectionId:18212:14495",
            "scopes": [],
            "hiddenFromPublishing": true,
            "resolvedType": "COLOR"
          }
        }
      },
      "apptopbartextcolordark": {
        "$value": "{Global.Text.textColorPrimaryDark}",
        "$type": "color",
        "$extensions": {
          "com.figma": {
            "id": "VariableID:18961:17144",
            "variableCollectionId": "VariableCollectionId:18212:14495",
            "scopes": [],
            "hiddenFromPublishing": true,
            "resolvedType": "COLOR"
          }
        }
      },
      "apptobbartabnavbottomborder": {
        "$value": "{SportBILD.blue.spobiBlue029}",
        "$type": "color",
        "$extensions": {
          "com.figma": {
            "id": "VariableID:19220:66794",
            "variableCollectionId": "VariableCollectionId:18212:14495",
            "scopes": [],
            "hiddenFromPublishing": true,
            "resolvedType": "COLOR"
          }
        }
      },
      "apptobbartabnavbottomborderdark": {
        "$value": "{SportBILD.blue.spobiBlue029}",
        "$type": "color",
        "$extensions": {
          "com.figma": {
            "id": "VariableID:19221:66795",
            "variableCollectionId": "VariableCollectionId:18212:14495",
            "scopes": [],
            "hiddenFromPublishing": true,
            "resolvedType": "COLOR"
          }
        }
      },
      "apptobbartabnavbottomborderactive": {
        "$value": "{BILD.gray.BILD085}",
        "$type": "color",
        "$extensions": {
          "com.figma": {
            "id": "VariableID:19221:66799",
            "variableCollectionId": "VariableCollectionId:18212:14495",
            "scopes": [],
            "hiddenFromPublishing": true,
            "resolvedType": "COLOR"
          }
        }
      },
      "apptobbartabnavbottomborderactivedark": {
        "$value": "{BILD.neutral.BILD100}",
        "$type": "color",
        "$extensions": {
          "com.figma": {
            "id": "VariableID:19221:66800",
            "variableCollectionId": "VariableCollectionId:18212:14495",
            "scopes": [],
            "hiddenFromPublishing": true,
            "resolvedType": "COLOR"
          }
        }
      }
    },
    "avatar": {
      "avatarlabelcolor": {
        "$value": "{BILD.gray.BILD045}",
        "$type": "color",
        "$description": "09-2025 css --article-author-name-color // Bild: 015; SpoBi: 045",
        "$extensions": {
          "com.figma": {
            "id": "VariableID:19001:8158",
            "variableCollectionId": "VariableCollectionId:18212:14495",
            "scopes": [],
            "hiddenFromPublishing": true,
            "resolvedType": "COLOR"
          }
        }
      },
      "avatarlabelcolordark": {
        "$value": "{BILD.gray.BILD093}",
        "$type": "color",
        "$description": "09-2025 css --article-author-name-color // Bild: 100; SpoBi: 093",
        "$extensions": {
          "com.figma": {
            "id": "VariableID:19003:10922",
            "variableCollectionId": "VariableCollectionId:18212:14495",
            "scopes": [],
            "hiddenFromPublishing": true,
            "resolvedType": "COLOR"
          }
        }
      },
      "avatarlabelcolorhover": {
        "$value": "{SportBILD.blue.spobiBlue029}",
        "$type": "color",
        "$description": "This variable is used for decorating the avatar text's underline color. Bild: 046; SpoBi: 029",
        "$extensions": {
          "com.figma": {
            "id": "VariableID:19030:1919",
            "variableCollectionId": "VariableCollectionId:18212:14495",
            "scopes": [],
            "hiddenFromPublishing": true,
            "resolvedType": "COLOR"
          }
        }
      }
    },
    "chipcoloractive": {
      "$value": "{SportBILD.blue.spobiBlue029}",
      "$type": "color",
      "$extensions": {
        "com.figma": {
          "id": "VariableID:20360:22977",
          "variableCollectionId": "VariableCollectionId:18212:14495",
          "scopes": [
            "ALL_SCOPES"
          ],
          "hiddenFromPublishing": false,
          "resolvedType": "COLOR"
        }
      }
    }
  }
}